CHANGES.rst
MANIFEST.in
README.rst
setup.cfg
setup.py
pyramid_caching/__init__.py
pyramid_caching/cache.py
pyramid_caching/events.py
pyramid_caching/exc.py
pyramid_caching/interfaces.py
pyramid_caching/key_versioner.py
pyramid_caching/serializers.py
pyramid_caching/versioner.py
pyramid_caching.egg-info/PKG-INFO
pyramid_caching.egg-info/SOURCES.txt
pyramid_caching.egg-info/dependency_links.txt
pyramid_caching.egg-info/requires.txt
pyramid_caching.egg-info/top_level.txt
pyramid_caching/ext/__init__.py
pyramid_caching/ext/metrics.py
pyramid_caching/ext/redis.py
pyramid_caching/ext/royal.py
pyramid_caching/ext/sqlalchemy.py