Metadata-Version: 1.1
Name: pyramid-caching
Version: 0.2.2
Summary: Key versioning caching for pyramid.
Home-page: https://github.com/hadrien/pyramid_caching
Author: Hadrien David
Author-email: hadrien+pypi@ectobal.com
License: UNKNOWN
Keywords: web wsgi pylons pyramid cache
Platform: UNKNOWN
Classifier: Development Status :: 3 - Alpha
Classifier: Environment :: Plugins
Classifier: Framework :: Pyramid
Classifier: Intended Audience :: Developers
Classifier: Programming Language :: Python
Classifier: Programming Language :: Python :: 2.7
Classifier: Programming Language :: Python :: Implementation :: CPython
Classifier: Topic :: Internet :: WWW/HTTP
Classifier: Topic :: Internet :: WWW/HTTP :: WSGI
